aerosim/__init__.py
aerosim/aerosim.py
aerosim-0.0.1.dist-info/METADATA
aerosim-0.0.1.dist-info/WHEEL
aerosim-0.0.1.dist-info/licenses/LICENSE
aerosim-0.0.1.dist-info/licenses/LICENSE-APACHE
aerosim-0.0.1.dist-info/RECORD
